pyawsmock/__init__.py
pyawsmock/config.py
pyawsmock/core.py
pyawsmock-0.1.2.dist-info/LICENSE
pyawsmock-0.1.2.dist-info/METADATA
pyawsmock-0.1.2.dist-info/WHEEL
pyawsmock-0.1.2.dist-info/top_level.txt
pyawsmock-0.1.2.dist-info/RECORD
