Metadata-Version: 2.1
Name: pyawsmock
Version: 0.1.2
Summary: Local AWS Mock for Python – Mock SSM Parameter Store, S3, CodeArtifact, and extendable AWS services
Author: coldsofttech
License: MIT
Requires-Python: >=3.10
License-File: LICENSE
Requires-Dist: boto3~=1.40.55
Requires-Dist: filelock~=3.20.0
Requires-Dist: crcmod~=1.7
